abook.py
abook-0.9.1.dist-info/LICENSE
abook-0.9.1.dist-info/METADATA
abook-0.9.1.dist-info/WHEEL
abook-0.9.1.dist-info/entry_points.txt
abook-0.9.1.dist-info/top_level.txt
abook-0.9.1.dist-info/RECORD
