Metadata-Version: 2.1
Name: abook
Version: 0.9.1
Summary: Python library to convert between Abook and vCard
Home-page: https://github.com/jspricke/python-abook
Author: Jochen Sprickerhof
Author-email: abook@jochen.sprickerhof.de
License: GPLv3+
Keywords: Abook
Classifier: Programming Language :: Python
Classifier: Development Status :: 4 - Beta
Classifier: Environment :: Console
Classifier: License :: OSI Approved :: GNU General Public License v3 or later (GPLv3+)
Classifier: Topic :: Software Development :: Libraries :: Python Modules
License-File: LICENSE
Requires-Dist: vobject
